ecodev_front/__init__.py
ecodev_front/accordion.py
ecodev_front/alert.py
ecodev_front/app_header.py
ecodev_front/app_layout.py
ecodev_front/app_logo.py
ecodev_front/app_name.py
ecodev_front/app_title.py
ecodev_front/aside_buttons.py
ecodev_front/aside_section.py
ecodev_front/assets/dashAgGridComponentFunctions.js
ecodev_front/button.py
ecodev_front/card.py
ecodev_front/constants.py
ecodev_front/container.py
ecodev_front/display_utils.py
ecodev_front/div.py
ecodev_front/divider.py
ecodev_front/documentation.py
ecodev_front/download_button.py
ecodev_front/drawer.py
ecodev_front/footer.py
ecodev_front/further_info.py
ecodev_front/graphs/__init__.py
ecodev_front/graphs/bar_chart.py
ecodev_front/graphs/fig_helpers.py
ecodev_front/graphs/fig_layout.py
ecodev_front/graphs/graph.py
ecodev_front/graphs/legend_position.py
ecodev_front/graphs/pie_chart.py
ecodev_front/graphs/plotly_tools.py
ecodev_front/graphs/scatter.py
ecodev_front/graphs/subplots.py
ecodev_front/graphs/sunburst.py
ecodev_front/group.py
ecodev_front/icon.py
ecodev_front/ids.py
ecodev_front/loading_overlay.py
ecodev_front/login.py
ecodev_front/modal.py
ecodev_front/module.py
ecodev_front/monitoring.py
ecodev_front/nav_items.py
ecodev_front/navbar.py
ecodev_front/navbar_page_icon.py
ecodev_front/navlink.py
ecodev_front/notification.py
ecodev_front/notifications.py
ecodev_front/page.py
ecodev_front/page_header.py
ecodev_front/page_layout.py
ecodev_front/report_value.py
ecodev_front/search_bar.py
ecodev_front/segment_control.py
ecodev_front/select.py
ecodev_front/shadow_box.py
ecodev_front/shadow_button.py
ecodev_front/stack.py
ecodev_front/stepper.py
ecodev_front/switch.py
ecodev_front/tables/__init__.py
ecodev_front/tables/column_def.py
ecodev_front/tables/data_table.py
ecodev_front/tables/data_table_button.py
ecodev_front/tabs.py
ecodev_front/text.py
ecodev_front/upload_box.py
ecodev_front-0.0.100.dist-info/LICENSE.md
ecodev_front-0.0.100.dist-info/METADATA
ecodev_front-0.0.100.dist-info/WHEEL
ecodev_front-0.0.100.dist-info/RECORD
